vending_machine.v
`timescale 1ns / 1ps
module vending_machine(clk, coins, rst,  choice, start, done, product, change);
input clk, start, choice, rst;
input [1:0] coins;
output done;
output reg [1:0] product;
output reg [2:0] change;

parameter chocalate = 1'b0, drink = 1'b1;
parameter s0 = 4'h0, s1 = 4'h1, s2 = 4'h2, s3 = 4'h3, s4 = 4'h4, s5 = 4'h5, s6 = 4'h6, s7 = 4'h7, s8 = 4'h8, s9 = 4'h9, s10 = 4'ha;
parameter one = 2'b00, two = 2'b01, five = 2'b10;

reg[3:0] state , next;

always @ (*) begin // state transition logic
    case (state)
    s0: next = start ? s1 : s0;

    s1: begin if (choice == chocalate) begin
        next = s2; end
        else if (choice == drink) begin
            next = s3;
        end
    end

    s2: begin case (coins)
    one: next = s4;
    two, five: next = s5;
    default: next = s2;
    endcase
    end

    s4: begin case (coins)
    one, two, five: next = s5;
    default: next = s4;
    endcase
    end

    s5: next = s0;

    s3: begin case(coins)
    five: next = s10;
    one: next = s6;
    two: next = s7;
    default: next = s3;
    endcase
    end

    s6: begin case(coins)
    five: next = s10;
    one: next = s7;
    two: next = s8;
    default: next = s6;
    endcase
    end

    s7: begin case(coins)
    five: next = s10;
    one: next = s8;
    two: next = s9;
    default: next = s7;
    endcase
    end

    s8: begin case(coins)
    five, two: next = s10;
    one: next = s9;
    default: next = s8;
    endcase
    end

    s9: begin case(coins)
    one, two, five: next = s10;
    default: next = s9;
    endcase
    end 

    s10: next = s0;

    default: next = s0;

    endcase
end

always @ (posedge clk) begin // state flip-flop
    if (rst)
    state <= s0;
    else
    state <= next;
end

assign done = ((state == s5) | (state == s10)); // done logic

always @ (state) begin // product logic 2'b01 = chocalate, 2'b10 = drink
    case (state)
    s5: product = 2'b01;
    s10: product = 2'b10;
    default: product = 2'b00;
    endcase
end

always @ (posedge clk) begin // change logic
    if(rst) begin
        change <= 3'b000;
    end
    else begin
    case(state)
    s2: case (coins)
    five: change = 3'b011;
    default: change = 3'b000;
    endcase

    s4: case (coins)
    two: change = 3'b001;
    five: change = 3'b100;
    default: change = 3'b000;
    endcase

    s6: case(coins)
    five: change = 3'b001;
    default: change = 3'b000;
    endcase

    s7: case(coins)
    five: change = 3'b010;
    default: change = 3'b000;
    endcase

    s8: case(coins)
    five: change = 3'b011;
    default: change = 3'b000;
    endcase

    s9: case(coins)
    two: change = 3'b001;
    five: change = 3'b100;
    default: change = 3'b000;
    endcase

    default: change = 3'b000;
    endcase
    end
end

endmodule

testbench.v
`timescale 1ns / 1ps
module testbench;
reg clk, start, choice, rst;
reg [1:0] coins;
wire done;
wire [1:0] product;
wire [2:0] change;

vending_machine dut(.clk(clk), .rst(rst), .start(start), .choice(choice), .coins(coins), .done(done), .product(product), .change(change));

initial begin
    clk = 1'b0;
    forever #5 clk = ~clk;
end

initial begin
    rst = 1'b0;
end

initial begin
    start = 1'b1;
end

initial begin
    #2 choice = 1'b0;
    forever #100 choice = ~choice;
end

initial begin
    #2 coins = 2'b01;
    #100 coins = 2'b00;
    #100 coins = 2'b10;
    #100 coins = 2'b01;
    #100 coins = 2'b00;
    #100 coins = 2'b10;
end

initial begin
    $dumpfile("v_m.vcd");
    $dumpvars(0, testbench);
    $monitor($time, " clk = %b, rst = %b, choice = %b, start = %b, coins = %2b, done = %b, product = %2b, change = %3b", clk, rst, choice, start, coins, done, product, change);
end

initial begin
    #1000 $finish;
end

endmodule

v_m.vcd
$date
	Fri Jul 11 19:00:40 2025
$end
$version
	Icarus Verilog
$end
$timescale
	1ps
$end
$scope module testbench $end
$var wire 2 ! product [1:0] $end
$var wire 1 " done $end
$var wire 3 # change [2:0] $end
$var reg 1 $ choice $end
$var reg 1 % clk $end
$var reg 2 & coins [1:0] $end
$var reg 1 ' rst $end
$var reg 1 ( start $end
$scope module dut $end
$var wire 1 $ choice $end
$var wire 1 % clk $end
$var wire 2 ) coins [1:0] $end
$var wire 1 " done $end
$var wire 1 ' rst $end
$var wire 1 ( start $end
$var parameter 1 * chocalate $end
$var parameter 1 + drink $end
$var parameter 2 , five $end
$var parameter 2 - one $end
$var parameter 4 . s0 $end
$var parameter 4 / s1 $end
$var parameter 4 0 s10 $end
$var parameter 4 1 s2 $end
$var parameter 4 2 s3 $end
$var parameter 4 3 s4 $end
$var parameter 4 4 s5 $end
$var parameter 4 5 s6 $end
$var parameter 4 6 s7 $end
$var parameter 4 7 s8 $end
$var parameter 4 8 s9 $end
$var parameter 2 9 two $end
$var reg 3 : change [2:0] $end
$var reg 4 ; next [3:0] $end
$var reg 2 < product [1:0] $end
$var reg 4 = state [3:0] $end
$upscope $end
$upscope $end
$enddefinitions $end
$comment Show the parameter values. $end
$dumpall
b1 9
b1001 8
b1000 7
b111 6
b110 5
b101 4
b100 3
b11 2
b10 1
b1010 0
b1 /
b0 .
b0 -
b10 ,
1+
0*
$end
#0
$dumpvars
bx =
bx <
b0 ;
bx :
bx )
1(
0'
bx &
0%
x$
bx #
x"
bx !
$end
#2000
b1 &
b1 )
0$
#5000
b0 !
b0 <
b1 ;
0"
b0 =
b0 #
b0 :
1%
#10000
0%
#15000
b10 ;
b1 =
1%
#20000
0%
#25000
b101 ;
b10 =
1%
#30000
0%
#35000
b1 !
b1 <
b0 ;
1"
b101 =
1%
#40000
0%
#45000
b0 !
b0 <
b1 ;
0"
b0 =
1%
#50000
0%
#55000
b10 ;
b1 =
1%
#60000
0%
#65000
b101 ;
b10 =
1%
#70000
0%
#75000
b1 !
b1 <
b0 ;
1"
b101 =
1%
#80000
0%
#85000
b0 !
b0 <
b1 ;
0"
b0 =
1%
#90000
0%
#95000
b10 ;
b1 =
1%
#100000
0%
#102000
b11 ;
b0 &
b0 )
1$
#105000
b110 ;
b11 =
1%
#110000
0%
#115000
b111 ;
b110 =
1%
#120000
0%
#125000
b1000 ;
b111 =
1%
#130000
0%
#135000
b1001 ;
b1000 =
1%
#140000
0%
#145000
b1010 ;
b1001 =
1%
#150000
0%
#155000
b10 !
b10 <
b0 ;
1"
b1010 =
1%
#160000
0%
#165000
b0 !
b0 <
b1 ;
0"
b0 =
1%
#170000
0%
#175000
b11 ;
b1 =
1%
#180000
0%
#185000
b110 ;
b11 =
1%
#190000
0%
#195000
b111 ;
b110 =
1%
#200000
0%
#202000
b1010 ;
b10 &
b10 )
0$
#205000
b10 !
b10 <
b0 ;
1"
b1010 =
b1 #
b1 :
1%
#210000
0%
#215000
b0 !
b0 <
b1 ;
0"
b0 =
b0 #
b0 :
1%
#220000
0%
#225000
b10 ;
b1 =
1%
#230000
0%
#235000
b101 ;
b10 =
1%
#240000
0%
#245000
b1 !
b1 <
b0 ;
1"
b101 =
b11 #
b11 :
1%
#250000
0%
#255000
b0 !
b0 <
b1 ;
0"
b0 =
b0 #
b0 :
1%
#260000
0%
#265000
b10 ;
b1 =
1%
#270000
0%
#275000
b101 ;
b10 =
1%
#280000
0%
#285000
b1 !
b1 <
b0 ;
1"
b101 =
b11 #
b11 :
1%
#290000
0%
#295000
b0 !
b0 <
b1 ;
0"
b0 =
b0 #
b0 :
1%
#300000
0%
#302000
b1 &
b1 )
1$
#305000
b11 ;
b1 =
1%
#310000
0%
#315000
b111 ;
b11 =
1%
#320000
0%
#325000
b1001 ;
b111 =
1%
#330000
0%
#335000
b1010 ;
b1001 =
1%
#340000
0%
#345000
b10 !
b10 <
b0 ;
1"
b1010 =
b1 #
b1 :
1%
#350000
0%
#355000
b0 !
b0 <
b1 ;
0"
b0 =
b0 #
b0 :
1%
#360000
0%
#365000
b11 ;
b1 =
1%
#370000
0%
#375000
b111 ;
b11 =
1%
#380000
0%
#385000
b1001 ;
b111 =
1%
#390000
0%
#395000
b1010 ;
b1001 =
1%
#400000
0%
#402000
b0 &
b0 )
0$
#405000
b10 !
b10 <
b0 ;
1"
b1010 =
1%
#410000
0%
#415000
b0 !
b0 <
b1 ;
0"
b0 =
1%
#420000
0%
#425000
b10 ;
b1 =
1%
#430000
0%
#435000
b100 ;
b10 =
1%
#440000
0%
#445000
b101 ;
b100 =
1%
#450000
0%
#455000
b1 !
b1 <
b0 ;
1"
b101 =
1%
#460000
0%
#465000
b0 !
b0 <
b1 ;
0"
b0 =
1%
#470000
0%
#475000
b10 ;
b1 =
1%
#480000
0%
#485000
b100 ;
b10 =
1%
#490000
0%
#495000
b101 ;
b100 =
1%
#500000
0%
#502000
b10 &
b10 )
1$
#505000
b1 !
b1 <
b0 ;
1"
b101 =
b100 #
b100 :
1%
#510000
0%
#515000
b0 !
b0 <
b1 ;
0"
b0 =
b0 #
b0 :
1%
#520000
0%
#525000
b11 ;
b1 =
1%
#530000
0%
#535000
b1010 ;
b11 =
1%
#540000
0%
#545000
b10 !
b10 <
b0 ;
1"
b1010 =
1%
#550000
0%
#555000
b0 !
b0 <
b1 ;
0"
b0 =
1%
#560000
0%
#565000
b11 ;
b1 =
1%
#570000
0%
#575000
b1010 ;
b11 =
1%
#580000
0%
#585000
b10 !
b10 <
b0 ;
1"
b1010 =
1%
#590000
0%
#595000
b0 !
b0 <
b1 ;
0"
b0 =
1%
#600000
0%
#602000
0$
#605000
b10 ;
b1 =
1%
#610000
0%
#615000
b101 ;
b10 =
1%
#620000
0%
#625000
b1 !
b1 <
b0 ;
1"
b101 =
b11 #
b11 :
1%
#630000
0%
#635000
b0 !
b0 <
b1 ;
0"
b0 =
b0 #
b0 :
1%
#640000
0%
#645000
b10 ;
b1 =
1%
#650000
0%
#655000
b101 ;
b10 =
1%
#660000
0%
#665000
b1 !
b1 <
b0 ;
1"
b101 =
b11 #
b11 :
1%
#670000
0%
#675000
b0 !
b0 <
b1 ;
0"
b0 =
b0 #
b0 :
1%
#680000
0%
#685000
b10 ;
b1 =
1%
#690000
0%
#695000
b101 ;
b10 =
1%
#700000
0%
#702000
1$
#705000
b1 !
b1 <
b0 ;
1"
b101 =
b11 #
b11 :
1%
#710000
0%
#715000
b0 !
b0 <
b1 ;
0"
b0 =
b0 #
b0 :
1%
#720000
0%
#725000
b11 ;
b1 =
1%
#730000
0%
#735000
b1010 ;
b11 =
1%
#740000
0%
#745000
b10 !
b10 <
b0 ;
1"
b1010 =
1%
#750000
0%
#755000
b0 !
b0 <
b1 ;
0"
b0 =
1%
#760000
0%
#765000
b11 ;
b1 =
1%
#770000
0%
#775000
b1010 ;
b11 =
1%
#780000
0%
#785000
b10 !
b10 <
b0 ;
1"
b1010 =
1%
#790000
0%
#795000
b0 !
b0 <
b1 ;
0"
b0 =
1%
#800000
0%
#802000
0$
#805000
b10 ;
b1 =
1%
#810000
0%
#815000
b101 ;
b10 =
1%
#820000
0%
#825000
b1 !
b1 <
b0 ;
1"
b101 =
b11 #
b11 :
1%
#830000
0%
#835000
b0 !
b0 <
b1 ;
0"
b0 =
b0 #
b0 :
1%
#840000
0%
#845000
b10 ;
b1 =
1%
#850000
0%
#855000
b101 ;
b10 =
1%
#860000
0%
#865000
b1 !
b1 <
b0 ;
1"
b101 =
b11 #
b11 :
1%
#870000
0%
#875000
b0 !
b0 <
b1 ;
0"
b0 =
b0 #
b0 :
1%
#880000
0%
#885000
b10 ;
b1 =
1%
#890000
0%
#895000
b101 ;
b10 =
1%
#900000
0%
#902000
1$
#905000
b1 !
b1 <
b0 ;
1"
b101 =
b11 #
b11 :
1%
#910000
0%
#915000
b0 !
b0 <
b1 ;
0"
b0 =
b0 #
b0 :
1%
#920000
0%
#925000
b11 ;
b1 =
1%
#930000
0%
#935000
b1010 ;
b11 =
1%
#940000
0%
#945000
b10 !
b10 <
b0 ;
1"
b1010 =
1%
#950000
0%
#955000
b0 !
b0 <
b1 ;
0"
b0 =
1%
#960000
0%
#965000
b11 ;
b1 =
1%
#970000
0%
#975000
b1010 ;
b11 =
1%
#980000
0%
#985000
b10 !
b10 <
b0 ;
1"
b1010 =
1%
#990000
0%
#995000
b0 !
b0 <
b1 ;
0"
b0 =
1%
